README.md
setup.cfg
setup.py
domaincheck/__init__.py
domaincheck/__main__.py
domaincheck/check.py
domaincheck/check_result.py
domaincheck/util.py
domaincheck.egg-info/PKG-INFO
domaincheck.egg-info/SOURCES.txt
domaincheck.egg-info/dependency_links.txt
domaincheck.egg-info/entry_points.txt
domaincheck.egg-info/requires.txt
domaincheck.egg-info/top_level.txt
domaincheck/checks/__init__.py
domaincheck/checks/dns_check.py