Metadata-Version: 1.0
Name: domaincheck
Version: 1.0.2
Summary: Domain availability check
Home-page: UNKNOWN
Author: Matthias Lohr
Author-email: matthias@lohr.me
License: UNKNOWN
Platform: UNKNOWN
